{
  "metadata": {
    "homeTitle": "BTH Expert — مكتب الدراسات البيئية المعتمد | وهران",
    "homeDescription": "مكتب دراسات معتمد من طرف وزارة البيئة الجزائرية. دراسات التأثير، دراسات الأخطار، تدقيقات الصحة والسلامة والبيئة والمطابقة التنظيمية في وهران وعلى كامل التراب الجزائري."
  },
  "nav": {
    "services": "الخدمات",
    "secteurs": "القطاعات",
    "equipe": "الفريق",
    "projets": "المشاريع",
    "blog": "المدونة",
    "contact": "اتصل بنا",
    "quote": "طلب عرض سعر"
  },
  "footer": {
    "rights": "جميع الحقوق محفوظة",
    "zones": "مناطق التدخل",
    "language": "اللغة"
  },
  "common": {
    "learnMore": "اعرف المزيد",
    "contactUs": "اتصل بنا"
  }
}